blindml/__init__.py
blindml/client.py
blindml/client_copy.py
blindml/client_new.py
blindml/client_old.py
blindml-0.1.2.dist-info/METADATA
blindml-0.1.2.dist-info/WHEEL
blindml-0.1.2.dist-info/top_level.txt
blindml-0.1.2.dist-info/RECORD
