Metadata-Version: 2.1
Name: blindml
Version: 0.1.2
Summary: A client library for FHE-enabled machine learning via BlindMLServer
Author-email: BlindML <info@blindml.com>
License: MIT
Classifier: Programming Language :: Python :: 3
Classifier: License :: OSI Approved :: MIT License
Classifier: Operating System :: OS Independent
Requires-Python: >=3.8.20
Requires-Dist: concrete-ml==1.4.0
Requires-Dist: requests>=2.28.0
